setup.py
etl_utils/__init__.py
etl_utils/_current_dir.py
etl_utils/buffer_logger.py
etl_utils/cache_utils.py
etl_utils/console_utils.py
etl_utils/design_pattern.py
etl_utils/dict_utils.py
etl_utils/entropy.py
etl_utils/extract_words.py
etl_utils/hash_utils.py
etl_utils/item_increment_id_dict.py
etl_utils/items_group_and_indexes.py
etl_utils/itertools_utils.py
etl_utils/json_utils.py
etl_utils/lazy_data.py
etl_utils/list_utils.py
etl_utils/mark_object_ids.py
etl_utils/nlp.py
etl_utils/object_utils.py
etl_utils/process_notifier.py
etl_utils/regexp_utils.py
etl_utils/slots_utils.py
etl_utils/speed.py
etl_utils/string_utils.py
etl_utils/unicode_utils.py
etl_utils/xml.py
etl_utils.egg-info/PKG-INFO
etl_utils.egg-info/SOURCES.txt
etl_utils.egg-info/dependency_links.txt
etl_utils.egg-info/not-zip-safe
etl_utils.egg-info/pbr.json
etl_utils.egg-info/requires.txt
etl_utils.egg-info/top_level.txt