Metadata-Version: 1.1
Name: etl-utils
Version: 0.1.10
Summary: etl utils
Home-page: http://17zuoye.github.io/etl_utils/
Author: David Chen
Author-email: mvjome@gmail.com
License: MIT
Platform: any
Classifier: Intended Audience :: Developers
Classifier: Operating System :: OS Independent
Classifier: Programming Language :: Python
Classifier: Topic :: Software Development :: Libraries :: Python Modules
